bson_timezone/__init__.py
bson_timezone/__version__.py
bson_timezone/tests/__init__.py
bson_timezone/tests/test_bson_timezone.py
bson_timezone-0.0.2.dist-info/METADATA
bson_timezone-0.0.2.dist-info/RECORD
bson_timezone-0.0.2.dist-info/WHEEL
bson_timezone-0.0.2.dist-info/top_level.txt
