Metadata-Version: 2.1
Name: bson-timezone
Version: 0.0.2
Summary: Provides timezone support for bson.json_util.dumps and bson.json_util.loads
Home-page: UNKNOWN
Author: AgileTek Engineering
License: UNKNOWN
Platform: UNKNOWN
Classifier: License :: OSI Approved :: GNU Affero General Public License v3
Classifier: Programming Language :: Python :: 3.6
Classifier: Natural Language :: English
Classifier: Operating System :: OS Independent
Provides-Extra: pre-commit
Provides-Extra: flake8
Provides-Extra: black
Requires-Dist: pymongo
Requires-Dist: pytz
Provides-Extra: black
Requires-Dist: black; extra == 'black'
Provides-Extra: flake8
Requires-Dist: flake8; extra == 'flake8'
Provides-Extra: pre-commit
Requires-Dist: pre-commit; extra == 'pre-commit'
